dvfile/__init__.py
dvfile/data.py
dvfile/dvtb.py
dvfile/singer.py
dvfile-0.2.0.dist-info/LICENSE
dvfile-0.2.0.dist-info/METADATA
dvfile-0.2.0.dist-info/WHEEL
dvfile-0.2.0.dist-info/top_level.txt
dvfile-0.2.0.dist-info/RECORD
